[
    {
        "type": "normal",
        "fileName": "day-green-version.svg",
        "backgroundColor": "#ffffff",
        "foregroundColor": "#000000",
        "strongColor": "#47a042",
        "weakColor": "#8cc569",
        "radarColor": "#47a042",
        "growingAnimation": true,
        "contribColors": [
            "#efefef",
            "#d8e887",
            "#8cc569",
            "#47a042",
            "#1d6a23"
        ]
    },
    {
        "type": "night-view",
        "fileName": "night-night-view.svg",
        "backgroundColor": "#00000f",
        "foregroundColor": "#eeeeff",
        "strongColor": "#ffc837",
        "weakColor": "#aaaaaa",
        "radarColor": "#ffc837",
        "growingAnimation": true,
        "contribColors": [
            "rgb(25, 60, 130)",
            "rgb(25, 90, 210)",
            "rgb(25, 120, 220)",
            "rgb(25, 150, 230)",
            "rgb(25, 165, 240)"
        ]
    }
]
